CHANGES.md
LICENSE
MANIFEST.in
README.md
setup.py
dj_livesettings.egg-info/PKG-INFO
dj_livesettings.egg-info/SOURCES.txt
dj_livesettings.egg-info/dependency_links.txt
dj_livesettings.egg-info/requires.txt
dj_livesettings.egg-info/top_level.txt
livesettings/__init__.py
livesettings/admin.py
livesettings/api.py
livesettings/forms.py
livesettings/models.py