Metadata-Version: 1.1
Name: dj-livesettings
Version: 0.1.3
Summary: Django app that provides possibility to add settings that can be changed in DB.
Home-page: https://github.com/oeegor/dj-livesettings
Author: Egor Orlov
Author-email: oeegor@gmail.com
License: MIT License
Platform: any
Classifier: Environment :: Web Environment
Classifier: Framework :: Django
Classifier: Intended Audience :: Developers
Classifier: License :: OSI Approved :: MIT License
Classifier: Operating System :: OS Independent
Classifier: Programming Language :: Python
Classifier: Programming Language :: Python :: 2.7
Classifier: Programming Language :: Python :: 3.4
Classifier: Programming Language :: Python :: 3.5
Classifier: Topic :: Internet :: WWW/HTTP
Classifier: Topic :: Internet :: WWW/HTTP :: Dynamic Content
